LICENSE
README.md
pyproject.toml
setup.cfg
setup.py
djangorestframework_more.egg-info/PKG-INFO
djangorestframework_more.egg-info/SOURCES.txt
djangorestframework_more.egg-info/dependency_links.txt
djangorestframework_more.egg-info/requires.txt
djangorestframework_more.egg-info/top_level.txt
rest_framework_more/__init__.py
rest_framework_more/filters.py
rest_framework_more/get_field_keys.py
rest_framework_more/mixins.py
rest_framework_more/renderers.py
rest_framework_more/serializers.py
rest_framework_more/subpaths.py
rest_framework_more/viewsets.py