Metadata-Version: 2.1
Name: djangorestframework-more
Version: 1.5.0
Summary: More Cool Django Rest Framework Stuff
Home-page: https://github.com/DanielJDufour/djangorestframework-more
Download-URL: https://github.com/DanielJDufour/djangorestframework-more/tarball/download
Author: Daniel J. Dufour
Author-email: daniel.j.dufour@gmail.com
License: UNKNOWN
Keywords: csv,django,django-rest-framework,drf,djangorestframework-csv,excel,filters,forms,models,pagination,xlsx
Platform: UNKNOWN
Classifier: Programming Language :: Python :: 3
Classifier: Operating System :: OS Independent
License-File: LICENSE
